metisse/__init__.py
metisse/clients/__init__.py
metisse/clients/android/__init__.py
metisse/clients/android/adb.py
metisse/clients/client.py
metisse/clients/ios/__init__.py
metisse/clients/ios/wda.py
metisse/example/__init__.py
metisse/example/example_data/icon/example_template_face.png
metisse/example/example_data/icon/example_template_hand.png
metisse/example/example_data/temp_image/tmp0.png
metisse/example/example_data/ui/gui_settings.py
metisse/example/example_data/ui/script_gui.py
metisse/example/example_data/ui/universal_script_gui_main.ui
metisse/example/example_data/ui/universal_script_gui_main_ui.py
metisse/example/example_data/ui/universal_script_gui_sub.ui
metisse/example/example_data/ui/universal_script_gui_sub2.ui
metisse/example/example_data/ui/universal_script_gui_sub2_ui.py
metisse/example/example_data/ui/universal_script_gui_sub3.ui
metisse/example/example_data/ui/universal_script_gui_sub3_ui.py
metisse/example/example_data/ui/universal_script_gui_sub_ui.py
metisse/example/generate_example.py
metisse/metisse.py
metisse/params.py
metisse/settings.py
metisse/template_metis.py
metisse/utils/__init__.py
metisse/utils/image_recognition.py
metisse/utils/metisse_log.py
metisse/utils/metisse_path.py
metisse/utils/opencv_utils.py
metisse/utils/ui_client.py
metisse-0.0.8.dist-info/LICENSE
metisse-0.0.8.dist-info/METADATA
metisse-0.0.8.dist-info/WHEEL
metisse-0.0.8.dist-info/RECORD
