Metadata-Version: 2.1
Name: metisse
Version: 0.0.8
Summary: A versatile and automated testing framework for games and apps on Android and iOS platforms
License: Apache-2.0
Author: weekanda7
Author-email: 87613475+weekanda7@users.noreply.github.com
Requires-Python: >=3.8,<3.11
Classifier: License :: OSI Approved :: Apache Software License
Classifier: Programming Language :: Python :: 3
Classifier: Programming Language :: Python :: 3.8
Classifier: Programming Language :: Python :: 3.9
Classifier: Programming Language :: Python :: 3.10
Requires-Dist: black (>=23.9.1,<24.0.0)
Requires-Dist: dill (==0.3.6)
Requires-Dist: facebook-wda (==1.4.6)
Requires-Dist: isort (>=5.12.0,<6.0.0)
Requires-Dist: numpy (==1.21.4)
Requires-Dist: opencv-python-headless (>=4.8.1.78,<5.0.0.0)
Requires-Dist: pillow (==9.4.0)
Requires-Dist: pyqt6 (==6.4.2)
Requires-Dist: pytest (==7.3.1)
Requires-Dist: tidevice (==0.9.12)
